phipsair/__init__.py
phipsair/__main__.py
phipsair/cli.py
phipsair/purifier.py
phipsair/py.typed
phipsair/coap/__init__.py
phipsair/coap/aiocoap_monkeypatch.py
phipsair/coap/client.py
phipsair/coap/encryption.py
phipsair-0.5.0.dist-info/LICENSE
phipsair-0.5.0.dist-info/METADATA
phipsair-0.5.0.dist-info/WHEEL
phipsair-0.5.0.dist-info/entry_points.txt
phipsair-0.5.0.dist-info/top_level.txt
phipsair-0.5.0.dist-info/RECORD
