Metadata-Version: 2.1
Name: phipsair
Version: 0.5.0
Summary: phipsair allows controlling Philips air purifiers via encrypted CoAP.
Home-page: https://github.com/mfrister/phipsair
Author: betaboon, Michael Frister
License: MIT
Project-URL: Release notes, https://github.com/mfrister/phipsair/blob/main/CHANGELOG.md
Project-URL: Bug Tracker, https://github.com/mfrister/phipsair/issues
Classifier: Programming Language :: Python :: 3
Classifier: License :: OSI Approved :: MIT License
Classifier: Operating System :: OS Independent
License-File: LICENSE
Requires-Dist: aiocoap (<0.5,>=0.4.1)
Requires-Dist: pycryptodomex (<4.0,>=3.13)
